gou2tool/__init__.py
gou2tool/core/__init__.py
gou2tool/core/container.py
gou2tool/core/instance.py
gou2tool/core/lang/__init__.py
gou2tool/core/lang/http_status_code.py
gou2tool/core/request/__init__.py
gou2tool/core/response/__init__.py
gou2tool/core/response/controller_path_type.py
gou2tool/core/response/json_result.py
gou2tool/core/response/page_result.py
gou2tool/core/response/r.py
gou2tool/core/response/result.py
gou2tool/util/__init__.py
gou2tool/util/address_util.py
gou2tool/util/company_util.py
gou2tool/util/date_util.py
gou2tool/util/db_template_util.py
gou2tool/util/email_util.py
gou2tool/util/env_util.py
gou2tool/util/file_util.py
gou2tool/util/id_util.py
gou2tool/util/list_util.py
gou2tool/util/path_util.py
gou2tool/util/phone_util.py
gou2tool/util/r_util.py
gou2tool/util/random_util.py
gou2tool/util/sql_util.py
gou2tool/util/str_util.py
gou2tool/util/time_util.py
gou2tool/util/tree_util.py
gou2tool/util/web_hook_util.py
gou2tool-0.2.41.dist-info/licenses/LICENSE
tests/__init__.py
tests/address_util.py
tests/company_util.py
tests/email_util.py
tests/id_util.py
tests/path_util.py
tests/phone_util.py
tests/r.py
tests/sql_util.py
tests/str_util.py
tests/web_hook_util.py
gou2tool-0.2.41.dist-info/METADATA
gou2tool-0.2.41.dist-info/WHEEL
gou2tool-0.2.41.dist-info/top_level.txt
gou2tool-0.2.41.dist-info/RECORD
