Metadata-Version: 2.4
Name: gou2tool
Version: 0.2.41
Summary: 🐶 Python工具类库 更加快速的开发项目 便捷优雅的使用类库
Home-page: https://gitee.com/kingood/gou2tool
Author: kingood
Author-email: wl4837@qq.com
Classifier: Programming Language :: Python :: 3
Classifier: License :: OSI Approved :: MIT License
Classifier: Operating System :: OS Independent
Requires-Python: >=3.6
License-File: LICENSE
Provides-Extra: dev
Requires-Dist: pytest>=6.0; extra == "dev"
Requires-Dist: twine>=3.0; extra == "dev"
Dynamic: author
Dynamic: author-email
Dynamic: classifier
Dynamic: description
Dynamic: description-content-type
Dynamic: home-page
Dynamic: license-file
Dynamic: provides-extra
Dynamic: requires-python
Dynamic: summary
